LICENSE
README.md
setup.py
src/__init__.py
src/generate_results_plot.py
src/inception.py
src/run.py
src/timing.py
src/uid.py
src/videoreader.py
src/videosum.py
src/_methods/__init__.py
src/_methods/inception.py
src/_methods/scda.py
src/_methods/time.py
src/_methods/uid.py
test/test_videosum.py
videosum.egg-info/PKG-INFO
videosum.egg-info/SOURCES.txt
videosum.egg-info/dependency_links.txt
videosum.egg-info/requires.txt
videosum.egg-info/top_level.txt