Metadata-Version: 2.1
Name: videosum
Version: 0.0.8
Summary: Python module to summarise a video into a collage.
Home-page: https://github.com/luiscarlosgph/videosum
Author: Luis C. Garcia-Peraza Herrera
Author-email: luiscarlos.gph@gmail.com
License: MIT License
License-File: LICENSE
